zenrows/__init__.py
zenrows/__version__.py
zenrows/client.py
zenrows-1.3.2.dist-info/LICENSE
zenrows-1.3.2.dist-info/METADATA
zenrows-1.3.2.dist-info/WHEEL
zenrows-1.3.2.dist-info/top_level.txt
zenrows-1.3.2.dist-info/RECORD
