Metadata-Version: 2.1
Name: zenrows
Version: 1.3.2
Summary: Python client for ZenRows API
Home-page: https://github.com/ZenRows/zenrows-python-sdk
Author: Ander Rodriguez
Author-email: ander@zenrows.com
License: MIT
Project-URL: Bug Tracker, https://github.com/ZenRows/zenrows-python-sdk/issues
Project-URL: Documentation, https://www.zenrows.com/documentation
Keywords: zenrows scraper scraping
Classifier: License :: OSI Approved :: MIT License
Classifier: Operating System :: OS Independent
Classifier: Programming Language :: Python
Classifier: Programming Language :: Python :: 3
Classifier: Programming Language :: Python :: 3.6
Classifier: Programming Language :: Python :: 3.7
Classifier: Programming Language :: Python :: 3.8
Classifier: Programming Language :: Python :: 3.9
Classifier: Topic :: Internet :: Proxy Servers
Classifier: Topic :: Internet :: WWW/HTTP
Classifier: Topic :: Software Development :: Libraries :: Python Modules
Requires-Python: >=3.6
License-File: LICENSE
